djangoldp_ep/__init__.py
djangoldp_ep/admin.py
djangoldp_ep/apps.py
djangoldp_ep/context_processors.py
djangoldp_ep/djangoldp_settings.py
djangoldp_ep/djangoldp_urls.py
djangoldp_ep/oidc_settings.py
djangoldp_ep/settings.py
djangoldp_ep/auth/__init__.py
djangoldp_ep/auth/backends.py
djangoldp_ep/filters/__init__.py
djangoldp_ep/filters/contribution_filter_backend.py
djangoldp_ep/filters/related_actor_filter_backend.py
djangoldp_ep/filters/updated_since_filter_backend.py
djangoldp_ep/management/commands/0524_migration_importer.py
djangoldp_ep/management/commands/create_annual_contributions.py
djangoldp_ep/management/commands/create_capital_distributions.py
djangoldp_ep/management/commands/remove_duplicated_relatedactors.py
djangoldp_ep/migrations/0001_initial.py
djangoldp_ep/migrations/0002_auto_20210114_1101.py
djangoldp_ep/migrations/0003_profile_user.py
djangoldp_ep/migrations/0004_auto_20210114_1652.py
djangoldp_ep/migrations/0005_auto_20210118_1407.py
djangoldp_ep/migrations/0006_auto_20210119_1237.py
djangoldp_ep/migrations/0007_auto_20210120_1213.py
djangoldp_ep/migrations/0008_auto_20210120_1215.py
djangoldp_ep/migrations/0009_auto_20210120_1439.py
djangoldp_ep/migrations/0009_auto_20210120_1911.py
djangoldp_ep/migrations/0010_auto_20210120_1442.py
djangoldp_ep/migrations/0011_auto_20210120_1450.py
djangoldp_ep/migrations/0012_auto_20210120_1553.py
djangoldp_ep/migrations/0013_merge_20210120_1916.py
djangoldp_ep/migrations/0014_auto_20210121_1750.py
djangoldp_ep/migrations/0015_auto_20210122_1044.py
djangoldp_ep/migrations/0016_auto_20210122_1146.py
djangoldp_ep/migrations/0017_actor_iban.py
djangoldp_ep/migrations/0018_auto_20210122_1229.py
djangoldp_ep/migrations/0019_auto_20210124_1728.py
djangoldp_ep/migrations/0020_auto_20210125_1131.py
djangoldp_ep/migrations/0021_auto_20210125_1559.py
djangoldp_ep/migrations/0022_auto_20210125_1606.py
djangoldp_ep/migrations/0023_auto_20210125_1646.py
djangoldp_ep/migrations/0024_auto_20210125_2207.py
djangoldp_ep-1.0.0.dist-info/METADATA
djangoldp_ep-1.0.0.dist-info/WHEEL
djangoldp_ep-1.0.0.dist-info/top_level.txt
djangoldp_ep-1.0.0.dist-info/RECORD
