Metadata-Version: 2.1
Name: djangoldp-ep
Version: 1.0.0
Summary: djangoldp package for Energie Partagee
Home-page: https://git.startinblox.com/djangoldp-packages/djangoldp-ep/
Author: Startin'blox
Author-email: jbaptiste@startinblox.com
License: MIT
Classifier: Programming Language :: Python :: 3
Requires-Dist: djangoldp~=3.1
Requires-Dist: djangoldp-account~=3.1
Requires-Dist: pandas~=2.2.3
Requires-Dist: openpyxl~=3.1.5
Requires-Dist: reportlab==3.6.13
Requires-Dist: xhtml2pdf~=0.2
Provides-Extra: include_package_data
Requires-Dist: True; extra == "include-package-data"
